Workbook

Sheet Summary
B2: 2022-2023 EIVY USA BOOKING PROGRAM
B4: SHIP TO : | E4: PO#
E6: TOTAL :
B9: BILL TO : | F9: DEADLINE - February 1, 2022
B15: DROP ONE:
C16: BASELAYER | E16: FLEECE | G16: ACCESSORIES
C17: ='Eivy 22-23 Drop One'!I339 -> 0 | E17: ='Eivy 22-23 Drop One'!I496 -> 0 | F17: ='Eivy 22-23 Drop One'!I562 -> 0
E19: DROP ONE TOTAL: | G19: =C17+E17+F17 -> 0
B22: DROP TWO:
C23: BASELAYER | E23: FLEECE | G23: ACCESSORIES
C24: ='Eivy 22-23 Drop Two'!I213 -> 0 | E24: ='Eivy 22-23 Drop Two'!I286 -> 0 | F24: ='Eivy 22-23 Drop Two'!I311 -> 0
C26: CARRY OVER | E26: DROP TWO TOTAL: | G26: =C24+E24+F24+C27 -> 0
C27: ='Eivy 22-23 Drop Two'!I465 -> 0
E30: ORDER TOTAL: | G30: =G26+G19 -> 0
B34: NOTES:
B44: CONTACT:
A45: Foundry Distribution - 3602 Via Terra Street, Salt Lake City, Utah 84115 p. 801.994.6484 e. info@foundrydist.com

Sheet Policy
B2: DISCOUNT STRUCTURE AND POLICY
C5: ORDER TOTAL | D5: VOLUME DISCOUNT
B6: *To qualify for booking terms a minimum order of $ 1,000 must be made by order deadline | C6: $ 2, 001 - $ 5,000 | D6: 0.03
B7: *All orders are subject to availability. | C7: $ 5,001 -10,000 | D7: 0.05
B8: *Orders received after booking deadline will not be eligible for discounts. | C8: $ 10,000 + | D8: 0.07
B10: CREDIT TERMS & LIMITS
B11: * To receive discounts order MUST be submitted by order deadline. All product is Subject To Prior Sale
B12: * Booking terms are COD from the date of shipment (On Approved Credit) If minimum booking volume is not met.
B13: * Booking terms are Net 60 Days if minimum booking is met. Late Payment of 2% monthly will be applied.
B14: * After the expiration date all backorders will be shipped on regular terms.
B15: * To qualify for Eivy Booking Terms your Nitro Snowboards Canada account must be current in good standing.
B16: * Discounts may be given as a credit at time of on-time payment, for dealers with previous payment history concerns.
B17: * Pricing may be adjusted for currency decline. All Pricing is in USD
B18: * Please fill out order form completely, including signature at bottom.
B19: * PDC's may be required on orders over $ 5,000.
B20: * All orders are subject to credit approval by Foundry Distribution and may be rejected without cause or liability.
B21: * If start ship and cancel dates are not filled in on the order form, product is to ship as ready.
... B48: ALL SALES ARE SUBJECT TO TERMS AND CONDITIONS OF NITRO SNOWBOARDS AUTHORIZED DEALER APPLICATION

Sheet Eivy 22-23 Drop One
A1: EAN | B1: Code | C1: Name | D1: Color | E1: Size | F1: Wholesale | G1: Retail | H1: Order Qty | I1: Ext
A2: BASELAYERS
A3: 7330057018950 | B3: A00189075-XXS | C3: Icecold Top | D3: Team Black | E3: XXS | F3: 47.5 | G3: 94.95 | I3: =F3*H3 -> 0
A4: 7330057018967 | B4: A00189075-XS | C4: Icecold Top | D4: Team Black | E4: XS | F4: 47.5 | G4: 94.95 | I4: =F4*H4 -> 0
A5: 7330057018974 | B5: A00189075-S | C5: Icecold Top | D5: Team Black | E5: S | F5: 47.5 | G5: 94.95 | I5: =F5*H5 -> 0
A6: 7330057018981 | B6: A00189075-M | C6: Icecold Top | D6: Team Black | E6: M | F6: 47.5 | G6: 94.95 | I6: =F6*H6 -> 0
A7: 7330057018998 | B7: A00189075-L | C7: Icecold Top | D7: Team Black | E7: L | F7: 47.5 | G7: 94.95 | I7: =F7*H7 -> 0
A8: 7330057019001 | B8: A00189075-XL | C8: Icecold Top | D8: Team Black | E8: XL | F8: 47.5 | G8: 94.95 | I8: =F8*H8 -> 0
A9: 7330057019018 | B9: A00189075-XXL | C9: Icecold Top | D9: Team Black | E9: XXL | F9: 47.5 | G9: 94.95 | I9: =F9*H9 -> 0
A10: 7330057019025 | B10: A00188075-XXS | C10: Icecold Tights | D10: Team Black | E10: XXS | F10: 42.5 | G10: 84.95 | I10: =F10*H10 -> 0
A11: 7330057019032 | B11: A00188075-XS | C11: Icecold Tights | D11: Team Black | E11: XS | F11: 42.5 | G11: 84.95 | I11: =F11*H11 -> 0
A12: 7330057019049 | B12: A00188075-S | C12: Icecold Tights | D12: Team Black | E12: S | F12: 42.5 | G12: 84.95 | I12: =F12*H12 -> 0
A13: 7330057019056 | B13: A00188075-M | C13: Icecold Tights | D13: Team Black | E13: M | F13: 42.5 | G13: 84.95 | I13: =F13*H13 -> 0
A14: 7330057019063 | B14: A00188075-L | C14: Icecold Tights | D14: Team Black | E14: L | F14: 42.5 | G14: 84.95 | I14: =F14*H14 -> 0
... A128: 7330057026962 | B128: A00247091-XXL | C128: Icecold Tights | D128: Pink Cheetah | E128: XXL | F128: 42.5 | G128: 84.95 | I128: =F128*H128 -> 0
A129: 7330057025279 | B129: A00191077-XXS | C129: Icecold Gaiter Top | D129: Snow Leopard | E129: XXS | F129: 47.5 | G129: 94.95 | I129: =F129*H129 -> 0
A130: 7330057025286 | B130: A00191077-XS | C130: Icecold Gaiter Top | D130: Snow Leopard | E130: XS | F130: 47.5 | G130: 94.95 | I130: =F130*H130 -> 0
A131: 7330057025293 | B131: A00191077-S | C131: Icecold Gaiter Top | D131: Snow Leopard | E131: S | F131: 47.5 | G131: 94.95 | I131: =F131*H131 -> 0
A132: 7330057025309 | B132: A00191077-M | C132: Icecold Gaiter Top | D132: Snow Leopard | E132: M | F132: 47.5 | G132: 94.95 | I132: =F132*H132 -> 0
A133: 7330057025316 | B133: A00191077-L | C133: Icecold Gaiter Top | D133: Snow Leopard | E133: L | F133: 47.5 | G133: 94.95 | I133: =F133*H133 -> 0
A134: 7330057025323 | B134: A00191077-XL | C134: Icecold Gaiter Top | D134: Snow Leopard | E134: XL | F134: 47.5 | G134: 94.95 | I134: =F134*H134 -> 0
A135: 7330057025330 | B135: A00191077-XXL | C135: Icecold Gaiter Top | D135: Snow Leopard | E135: XXL | F135: 47.5 | G135: 94.95 | I135: =F135*H135 -> 0
A136: 7330057019797 | B136: A00188077-XXS | C136: Icecold Tights | D136: Snow Leopard | E136: XXS | F136: 42.5 | G136: 84.95 | I136: =F136*H136 -> 0
A137: 7330057019803 | B137: A00188077-XS | C137: Icecold Tights | D137: Snow Leopard | E137: XS | F137: 42.5 | G137: 84.95 | I137: =F137*H137 -> 0
A138: 7330057019810 | B138: A00188077-S | C138: Icecold Tights | D138: Snow Leopard | E138: S | F138: 42.5 | G138: 84.95 | I138: =F138*H138 -> 0
A139: 7330057019827 | B139: A00188077-M | C139: Icecold Tights | D139: Snow Leopard | E139: M | F139: 42.5 | G139: 84.95 | I139: =F139*H139 -> 0
A140: 7330057019834 | B140: A00188077-L | C140: Icecold Tights | D140: Snow Leopard | E140: L | F140: 42.5 | G140: 84.95 | I140: =F140*H140 -> 0
A141: 7330057019841 | B141: A00188077-XL | C141: Icecold Tights | D141: Snow Leopard | E141: XL | F141: 42.5 | G141: 84.95 | I141: =F141*H141 -> 0
A142: 7330057019858 | B142: A00188077-XXL | C142: Icecold Tights | D142: Snow Leopard | E142: XXL | F142: 42.5 | G142: 84.95 | I142: =F142*H142 -> 0
A143: 7330057026979 | B143: A00240092-XXS | C143: Icecold Gaiter Top | D143: Abstract Shapes | E143: XXS | F143: 47.5 | G143: 94.95 | I143: =F143*H143 -> 0
A144: 7330057026986 | B144: A00240092-XS | C144: Icecold Gaiter Top | D144: Abstract Shapes | E144: XS | F144: 47.5 | G144: 94.95 | I144: =F144*H144 -> 0
A145: 7330057026993 | B145: A00240092-S | C145: Icecold Gaiter Top | D145: Abstract Shapes | E145: S | F145: 47.5 | G145: 94.95 | I145: =F145*H145 -> 0
A146: 7330057027006 | B146: A00240092-M | C146: Icecold Gaiter Top | D146: Abstract Shapes | E146: M | F146: 47.5 | G146: 94.95 | I146: =F146*H146 -> 0
A147: 7330057027013 | B147: A00240092-L | C147: Icecold Gaiter Top | D147: Abstract Shapes | E147: L | F147: 47.5 | G147: 94.95 | I147: =F147*H147 -> 0
... A338: 7330057028089 | B338: A00247095-XXL | C338: Icecold Tights | D338: Black & Offwhite | E338: XXL | F338: 42.5 | G338: 84.95 | I338: =F338*H338 -> 0
G339: Total: | H339: =SUM(H3:H338) -> 0 | I339: =SUM(I3:I338) -> 0
A341: FLEECE
A342: 7330057021752 | B342: A00198075-XXS | C342: Peg Cropped Fleece | D342: Team Black | E342: XXS | F342: 47.5 | G342: 94.95 | I342: =F342*H342 -> 0
A343: 7330057021769 | B343: A00198075-XS | C343: Peg Cropped Fleece | D343: Team Black | E343: XS | F343: 47.5 | G343: 94.95 | I343: =F343*H343 -> 0
A344: 7330057021776 | B344: A00198075-S | C344: Peg Cropped Fleece | D344: Team Black | E344: S | F344: 47.5 | G344: 94.95 | I344: =F344*H344 -> 0
A345: 7330057021783 | B345: A00198075-M | C345: Peg Cropped Fleece | D345: Team Black | E345: M | F345: 47.5 | G345: 94.95 | I345: =F345*H345 -> 0
A346: 7330057021790 | B346: A00198075-L | C346: Peg Cropped Fleece | D346: Team Black | E346: L | F346: 47.5 | G346: 94.95 | I346: =F346*H346 -> 0
A347: 7330057021806 | B347: A00198075-XL | C347: Peg Cropped Fleece | D347: Team Black | E347: XL | F347: 47.5 | G347: 94.95 | I347: =F347*H347 -> 0
A348: 7330057021813 | B348: A00198075-XXL | C348: Peg Cropped Fleece | D348: Team Black | E348: XXL | F348: 47.5 | G348: 94.95 | I348: =F348*H348 -> 0
A349: 7330057028096 | B349: A00249080-XXS | C349: Peg Cropped Fleece | D349: Team Leopard | E349: XXS | F349: 47.5 | G349: 94.95 | I349: =F349*H349 -> 0
A350: 7330057028102 | B350: A00249080-XS | C350: Peg Cropped Fleece | D350: Team Leopard | E350: XS | F350: 47.5 | G350: 94.95 | I350: =F350*H350 -> 0
A351: 7330057028119 | B351: A00249080-S | C351: Peg Cropped Fleece | D351: Team Leopard | E351: S | F351: 47.5 | G351: 94.95 | I351: =F351*H351 -> 0
A352: 7330057028126 | B352: A00249080-M | C352: Peg Cropped Fleece | D352: Team Leopard | E352: M | F352: 47.5 | G352: 94.95 | I352: =F352*H352 -> 0
A353: 7330057028133 | B353: A00249080-L | C353: Peg Cropped Fleece | D353: Team Leopard | E353: L | F353: 47.5 | G353: 94.95 | I353: =F353*H353 -> 0
... A495: 7330057028850 | B495: A00253015-XXL | C495: Redwood Sherpa Coat | D495: Navy | E495: XXL | F495: 80 | G495: 159.95 | I495: =F495*H495 -> 0
G496: Total: | H496: =SUM(H342:H495) -> 0 | I496: =SUM(I342:I495) -> 0
A498: ACCESSORIES
A499: 7330057028867 | B499: A00254009-36-38 | C499: Cheerleader Wool Socks | D499: Wine | E499: 36-38 | F499: 20 | G499: 39.95 | I499: =F499*H499 -> 0
A500: 7330057028874 | B500: A00254009-39-41 | C500: Cheerleader Wool Socks | D500: Wine | E500: 39-41 | F500: 20 | G500: 39.95 | I500: =F500*H500 -> 0
A501: 7330057028881 | B501: A00254029-36-38 | C501: Cheerleader Wool Socks | D501: Forest Green | E501: 36-38 | F501: 20 | G501: 39.95 | I501: =F501*H501 -> 0
A502: 7330057028898 | B502: A00254029-39-41 | C502: Cheerleader Wool Socks | D502: Forest Green | E502: 39-41 | F502: 20 | G502: 39.95 | I502: =F502*H502 -> 0
A503: 7330057028904 | B503: A00254040-36-38 | C503: Cheerleader Wool Socks | D503: Rust | E503: 36-38 | F503: 20 | G503: 39.95 | I503: =F503*H503 -> 0
A504: 7330057028911 | B504: A00254040-39-41 | C504: Cheerleader Wool Socks | D504: Rust | E504: 39-41 | F504: 20 | G504: 39.95 | I504: =F504*H504 -> 0
A505: 7330057023244 | B505: A00206064-36-38 | C505: Cheerleader Wool Socks | D505: Raspberry | E505: 36-38 | F505: 20 | G505: 39.95 | I505: =F505*H505 -> 0
A506: 7330057023251 | B506: A00206064-39-41 | C506: Cheerleader Wool Socks | D506: Raspberry | E506: 39-41 | F506: 20 | G506: 39.95 | I506: =F506*H506 -> 0
A507: 7330057023220 | B507: A00206010-36-38 | C507: Cheerleader Wool Socks | D507: Leopard | E507: 36-38 | F507: 20 | G507: 39.95 | I507: =F507*H507 -> 0
A508: 7330057023237 | B508: A00206010-39-41 | C508: Cheerleader Wool Socks | D508: Leopard | E508: 39-41 | F508: 20 | G508: 39.95 | I508: =F508*H508 -> 0
A509: 7330057028928 | B509: A00254091-36-38 | C509: Cheerleader Wool Socks | D509: Pink Cheetah | E509: 36-38 | F509: 20 | G509: 39.95 | I509: =F509*H509 -> 0
A510: 7330057028935 | B510: A00254091-39-41 | C510: Cheerleader Wool Socks | D510: Pink Cheetah | E510: 39-41 | F510: 20 | G510: 39.95 | I510: =F510*H510 -> 0
... A529: 7330057029024 | B529: A00257091-ONESIZ | C529: Hinge Balaclava | D529: Pink Cheetah | E529: OS | F529: 18 | G529: 35.95 | I529: =F529*H529 -> 0
A530: 7330057031232 | B530: A00257064-ONESIZ | C530: Hinge Balaclava | D530: Raspberry | E530: OS | F530: 18 | G530: 35.95 | I530: =F530*H530 -> 0
A531: 7330057023435 | B531: A00209001-ONESIZ | C531: Tubular Fleece Neckwarmer | D531: Black | E531: OS | F531: 18 | G531: 35.95 | I531: =F531*H531 -> 0
A532: 7330057029031 | B532: A00258010-ONESIZ | C532: Tubular Fleece Neckwarmer | D532: Leopard | E532: OS | F532: 18 | G532: 35.95 | I532: =F532*H532 -> 0
A533: 7330057029048 | B533: A00258092-ONESIZ | C533: Tubular Fleece Neckwarmer | D533: Abstract Shapes | E533: OS | F533: 18 | G533: 35.95 | I533: =F533*H533 -> 0
A534: 7330057029055 | B534: A00258094-ONESIZ | C534: Tubular Fleece Neckwarmer | D534: MX Pink | E534: OS | F534: 18 | G534: 35.95 | I534: =F534*H534 -> 0
A535: 7330057029062 | B535: A00259001-ONESIZ | C535: Mandy Fleece Balaclava | D535: Black | E535: OS | F535: 30 | G535: 59.95 | I535: =F535*H535 -> 0
A536: 7330057029079 | B536: A00259010-ONESIZ | C536: Mandy Fleece Balaclava | D536: Leopard | E536: OS | F536: 30 | G536: 59.95 | I536: =F536*H536 -> 0
A537: 7330057029086 | B537: A00259092-ONESIZ | C537: Mandy Fleece Balaclava | D537: Abstract Shapes | E537: OS | F537: 30 | G537: 59.95 | I537: =F537*H537 -> 0
A538: 7330057023503 | B538: A00211079-ONESIZ | C538: Mandy Fleece Balaclava | D538: Cheetah | E538: OS | F538: 30 | G538: 59.95 | I538: =F538*H538 -> 0
A539: 7330057029093 | B539: A00259094-ONESIZ | C539: Mandy Fleece Balaclava | D539: MX Pink | E539: OS | F539: 30 | G539: 59.95 | I539: =F539*H539 -> 0
A540: 7330057029109 | B540: A00260029-ONESIZ | C540: Tubular Sherpa Neckwarmer | D540: Forest Green | E540: OS | F540: 18 | G540: 35.95 | I540: =F540*H540 -> 0
A541: 7330057029116 | B541: A00260040-ONESIZ | C541: Tubular Sherpa Neckwarmer | D541: Rust | E541: OS | F541: 18 | G541: 35.95 | I541: =F541*H541 -> 0
A542: 7330057029123 | B542: A00260064-ONESIZ | C542: Tubular Sherpa Neckwarmer | D542: Raspberry | E542: OS | F542: 18 | G542: 35.95 | I542: =F542*H542 -> 0
... A561: 7330057029260 | B561: A00266064-ONESIZ | C561: Flap Sherpa Cap | D561: Raspberry | E561: OS | F561: 30 | G561: 59.95 | I561: =F561*H561 -> 0
G562: Total: | H562: =SUM(H499:H561) -> 0 | I562: =SUM(I499:I561) -> 0

Sheet Eivy 22-23 Drop Two
A1: EAN | B1: Code | C1: Name | D1: Color | E1: Size | F1: Wholesale | G1: Retail | H1: Order Qty | I1: Ext
A2: Baselayer
A3: 7330057023657 | B3: A00219086-XXS | C3: Icecold Rib Top | D3: Faded Amber | E3: XXS | F3: 47.5 | G3: 94.95 | I3: =H3*F3 -> 0
A4: 7330057023664 | B4: A00219086-XS | C4: Icecold Rib Top | D4: Faded Amber | E4: XS | F4: 47.5 | G4: 94.95 | I4: =H4*F4 -> 0
A5: 7330057023671 | B5: A00219086-S | C5: Icecold Rib Top | D5: Faded Amber | E5: S | F5: 47.5 | G5: 94.95 | I5: =H5*F5 -> 0
A6: 7330057023688 | B6: A00219086-M | C6: Icecold Rib Top | D6: Faded Amber | E6: M | F6: 47.5 | G6: 94.95 | I6: =H6*F6 -> 0
A7: 7330057023695 | B7: A00219086-L | C7: Icecold Rib Top | D7: Faded Amber | E7: L | F7: 47.5 | G7: 94.95 | I7: =H7*F7 -> 0
A8: 7330057023701 | B8: A00219086-XL | C8: Icecold Rib Top | D8: Faded Amber | E8: XL | F8: 47.5 | G8: 94.95 | I8: =H8*F8 -> 0
A9: 7330057023718 | B9: A00219086-XXL | C9: Icecold Rib Top | D9: Faded Amber | E9: XXL | F9: 47.5 | G9: 94.95 | I9: =H9*F9 -> 0
A10: 7330057023725 | B10: A00222086-XXS | C10: Icecold Rib Tights | D10: Faded Amber | E10: XXS | F10: 42.5 | G10: 84.95 | I10: =H10*F10 -> 0
A11: 7330057023732 | B11: A00222086-XS | C11: Icecold Rib Tights | D11: Faded Amber | E11: XS | F11: 42.5 | G11: 84.95 | I11: =H11*F11 -> 0
A12: 7330057023749 | B12: A00222086-S | C12: Icecold Rib Tights | D12: Faded Amber | E12: S | F12: 42.5 | G12: 84.95 | I12: =H12*F12 -> 0
A13: 7330057023756 | B13: A00222086-M | C13: Icecold Rib Tights | D13: Faded Amber | E13: M | F13: 42.5 | G13: 84.95 | I13: =H13*F13 -> 0
A14: 7330057023763 | B14: A00222086-L | C14: Icecold Rib Tights | D14: Faded Amber | E14: L | F14: 42.5 | G14: 84.95 | I14: =H14*F14 -> 0
... A82: 7330057024449 | B82: A00222088-S | C82: Icecold Rib Tights | D82: Faded Oak | E82: S | F82: 42.5 | G82: 84.95 | I82: =H82*F82 -> 0
A83: 7330057024456 | B83: A00222088-M | C83: Icecold Rib Tights | D83: Faded Oak | E83: M | F83: 42.5 | G83: 84.95 | I83: =H83*F83 -> 0
A84: 7330057024463 | B84: A00222088-L | C84: Icecold Rib Tights | D84: Faded Oak | E84: L | F84: 42.5 | G84: 84.95 | I84: =H84*F84 -> 0
A85: 7330057024470 | B85: A00222088-XL | C85: Icecold Rib Tights | D85: Faded Oak | E85: XL | F85: 42.5 | G85: 84.95 | I85: =H85*F85 -> 0
A86: 7330057024487 | B86: A00222088-XXL | C86: Icecold Rib Tights | D86: Faded Oak | E86: XXL | F86: 42.5 | G86: 84.95 | I86: =H86*F86 -> 0
A87: 7330057024494 | B87: A00224088-XXS | C87: Rider Rib Sports Bra | D87: Faded Oak | E87: XXS | F87: 25 | G87: 49.95 | I87: =H87*F87 -> 0
A88: 7330057024500 | B88: A00224088-XS | C88: Rider Rib Sports Bra | D88: Faded Oak | E88: XS | F88: 25 | G88: 49.95 | I88: =H88*F88 -> 0
A89: 7330057024517 | B89: A00224088-S | C89: Rider Rib Sports Bra | D89: Faded Oak | E89: S | F89: 25 | G89: 49.95 | I89: =H89*F89 -> 0
A90: 7330057024524 | B90: A00224088-M | C90: Rider Rib Sports Bra | D90: Faded Oak | E90: M | F90: 25 | G90: 49.95 | I90: =H90*F90 -> 0
A91: 7330057024531 | B91: A00224088-L | C91: Rider Rib Sports Bra | D91: Faded Oak | E91: L | F91: 25 | G91: 49.95 | I91: =H91*F91 -> 0
A92: 7330057024548 | B92: A00224088-XL | C92: Rider Rib Sports Bra | D92: Faded Oak | E92: XL | F92: 25 | G92: 49.95 | I92: =H92*F92 -> 0
A93: 7330057024555 | B93: A00224088-XXL | C93: Rider Rib Sports Bra | D93: Faded Oak | E93: XXL | F93: 25 | G93: 49.95 | I93: =H93*F93 -> 0
A94: 7330057024562 | B94: A00221088-XXS | C94: Venture Rib Top | D94: Faded Oak | E94: XXS | F94: 47.5 | G94: 94.95 | I94: =H94*F94 -> 0
... A142: 7330057025040 | B142: A00223089-XXL | C142: Harlem Rib Travel Pants | D142: Faded Woodrose | E142: XXL | F142: 47.5 | G142: 94.95 | I142: =H142*F142 -> 0
A143: 7330057029277 | B143: A00267098-XXS | C143: Icecold Rib Top | D143: Deep Sea | E143: XXS | F143: 47.5 | G143: 94.95 | I143: =H143*F143 -> 0
A144: 7330057029284 | B144: A00267098-XS | C144: Icecold Rib Top | D144: Deep Sea | E144: XS | F144: 47.5 | G144: 94.95 | I144: =H144*F144 -> 0
A145: 7330057029291 | B145: A00267098-S | C145: Icecold Rib Top | D145: Deep Sea | E145: S | F145: 47.5 | G145: 94.95 | I145: =H145*F145 -> 0
A146: 7330057029307 | B146: A00267098-M | C146: Icecold Rib Top | D146: Deep Sea | E146: M | F146: 47.5 | G146: 94.95 | I146: =H146*F146 -> 0
A147: 7330057029314 | B147: A00267098-L | C147: Icecold Rib Top | D147: Deep Sea | E147: L | F147: 47.5 | G147: 94.95 | I147: =H147*F147 -> 0
A148: 7330057029321 | B148: A00267098-XL | C148: Icecold Rib Top | D148: Deep Sea | E148: XL | F148: 47.5 | G148: 94.95 | I148: =H148*F148 -> 0
A149: 7330057029338 | B149: A00267098-XXL | C149: Icecold Rib Top | D149: Deep Sea | E149: XXL | F149: 47.5 | G149: 94.95 | I149: =H149*F149 -> 0
A150: 7330057029345 | B150: A00271098-XXS | C150: Icecold Rib Tights | D150: Deep Sea | E150: XXS | F150: 42.5 | G150: 84.95 | I150: =H150*F150 -> 0
A151: 7330057029352 | B151: A00271098-XS | C151: Icecold Rib Tights | D151: Deep Sea | E151: XS | F151: 42.5 | G151: 84.95 | I151: =H151*F151 -> 0
A152: 7330057029369 | B152: A00271098-S | C152: Icecold Rib Tights | D152: Deep Sea | E152: S | F152: 42.5 | G152: 84.95 | I152: =H152*F152 -> 0
A153: 7330057029376 | B153: A00271098-M | C153: Icecold Rib Tights | D153: Deep Sea | E153: M | F153: 42.5 | G153: 84.95 | I153: =H153*F153 -> 0
A154: 7330057029383 | B154: A00271098-L | C154: Icecold Rib Tights | D154: Deep Sea | E154: L | F154: 42.5 | G154: 84.95 | I154: =H154*F154 -> 0
... A212: 7330057029963 | B212: A00272099-XXL | C212: Harlem Rib Travel Pants | D212: Deep Purple | E212: XXL | F212: 47.5 | G212: 94.95 | I212: =H212*F212 -> 0
G213: Total: | H213: =SUM(H3:H212) -> 0 | I213: =SUM(I3:I212) -> 0
A215: FLEECE
A216: 7330057025958 | B216: A00235086-XXS | C216: Redwood Sherpa Jacket | D216: Faded Amber | E216: XXS | F216: 60 | G216: 119.95 | I216: =H216*F216 -> 0
A217: 7330057025965 | B217: A00235086-XS | C217: Redwood Sherpa Jacket | D217: Faded Amber | E217: XS | F217: 60 | G217: 119.95 | I217: =H217*F217 -> 0
A218: 7330057025972 | B218: A00235086-S | C218: Redwood Sherpa Jacket | D218: Faded Amber | E218: S | F218: 60 | G218: 119.95 | I218: =H218*F218 -> 0
A219: 7330057025989 | B219: A00235086-M | C219: Redwood Sherpa Jacket | D219: Faded Amber | E219: M | F219: 60 | G219: 119.95 | I219: =H219*F219 -> 0
A220: 7330057025996 | B220: A00235086-L | C220: Redwood Sherpa Jacket | D220: Faded Amber | E220: L | F220: 60 | G220: 119.95 | I220: =H220*F220 -> 0
A221: 7330057026009 | B221: A00235086-XL | C221: Redwood Sherpa Jacket | D221: Faded Amber | E221: XL | F221: 60 | G221: 119.95 | I221: =H221*F221 -> 0
A222: 7330057026016 | B222: A00235086-XXL | C222: Redwood Sherpa Jacket | D222: Faded Amber | E222: XXL | F222: 60 | G222: 119.95 | I222: =H222*F222 -> 0
A223: 7330057026023 | B223: A00235087-XXS | C223: Redwood Sherpa Jacket | D223: Faded Cloud | E223: XXS | F223: 60 | G223: 119.95 | I223: =H223*F223 -> 0
A224: 7330057026030 | B224: A00235087-XS | C224: Redwood Sherpa Jacket | D224: Faded Cloud | E224: XS | F224: 60 | G224: 119.95 | I224: =H224*F224 -> 0
A225: 7330057026047 | B225: A00235087-S | C225: Redwood Sherpa Jacket | D225: Faded Cloud | E225: S | F225: 60 | G225: 119.95 | I225: =H225*F225 -> 0
A226: 7330057026054 | B226: A00235087-M | C226: Redwood Sherpa Jacket | D226: Faded Cloud | E226: M | F226: 60 | G226: 119.95 | I226: =H226*F226 -> 0
A227: 7330057026061 | B227: A00235087-L | C227: Redwood Sherpa Jacket | D227: Faded Cloud | E227: L | F227: 60 | G227: 119.95 | I227: =H227*F227 -> 0
... A243: 7330057026221 | B243: A00235089-XXL | C243: Redwood Sherpa Jacket | D243: Faded Woodrose | E243: XXL | F243: 60 | G243: 119.95 | I243: =H243*F243 -> 0
A244: 7330057030952 | B244: A00273098-XXS | C244: Redwood Sherpa Jacket | D244: Deep Sea | E244: XXS | F244: 60 | G244: 119.95 | I244: =H244*F244 -> 0
A245: 7330057030969 | B245: A00273098-XS | C245: Redwood Sherpa Jacket | D245: Deep Sea | E245: XS | F245: 60 | G245: 119.95 | I245: =H245*F245 -> 0
A246: 7330057030976 | B246: A00273098-S | C246: Redwood Sherpa Jacket | D246: Deep Sea | E246: S | F246: 60 | G246: 119.95 | I246: =H246*F246 -> 0
A247: 7330057030983 | B247: A00273098-M | C247: Redwood Sherpa Jacket | D247: Deep Sea | E247: M | F247: 60 | G247: 119.95 | I247: =H247*F247 -> 0
A248: 7330057030990 | B248: A00273098-L | C248: Redwood Sherpa Jacket | D248: Deep Sea | E248: L | F248: 60 | G248: 119.95 | I248: =H248*F248 -> 0
A249: 7330057031003 | B249: A00273098-XL | C249: Redwood Sherpa Jacket | D249: Deep Sea | E249: XL | F249: 60 | G249: 119.95 | I249: =H249*F249 -> 0
A250: 7330057031010 | B250: A00273098-XXL | C250: Redwood Sherpa Jacket | D250: Deep Sea | E250: XXL | F250: 60 | G250: 119.95 | I250: =H250*F250 -> 0
A251: 7330057031027 | B251: A00273099-XXS | C251: Redwood Sherpa Jacket | D251: Deep Purple | E251: XXS | F251: 60 | G251: 119.95 | I251: =H251*F251 -> 0
A252: 7330057031034 | B252: A00273099-XS | C252: Redwood Sherpa Jacket | D252: Deep Purple | E252: XS | F252: 60 | G252: 119.95 | I252: =H252*F252 -> 0
A253: 7330057031041 | B253: A00273099-S | C253: Redwood Sherpa Jacket | D253: Deep Purple | E253: S | F253: 60 | G253: 119.95 | I253: =H253*F253 -> 0
A254: 7330057031058 | B254: A00273099-M | C254: Redwood Sherpa Jacket | D254: Deep Purple | E254: M | F254: 60 | G254: 119.95 | I254: =H254*F254 -> 0
A255: 7330057031065 | B255: A00273099-L | C255: Redwood Sherpa Jacket | D255: Deep Purple | E255: L | F255: 60 | G255: 119.95 | I255: =H255*F255 -> 0
... A258: 7330057030259 | B258: A00236086-XXS | C258: Lumberjackie Sherpa Vest | D258: Faded Amber | E258: XXS | F258: 60 | G258: 119.95 | I258: =H258*F258 -> 0
A259: 7330057026238 | B259: A00236086-XS | C259: Lumberjackie Sherpa Vest | D259: Faded Amber | E259: XS | F259: 60 | G259: 119.95 | I259: =H259*F259 -> 0
A260: 7330057026245 | B260: A00236086-S | C260: Lumberjackie Sherpa Vest | D260: Faded Amber | E260: S | F260: 60 | G260: 119.95 | I260: =H260*F260 -> 0
A261: 7330057026252 | B261: A00236086-M | C261: Lumberjackie Sherpa Vest | D261: Faded Amber | E261: M | F261: 60 | G261: 119.95 | I261: =H261*F261 -> 0
A262: 7330057026269 | B262: A00236086-L | C262: Lumberjackie Sherpa Vest | D262: Faded Amber | E262: L | F262: 60 | G262: 119.95 | I262: =H262*F262 -> 0
A263: 7330057026276 | B263: A00236086-XL | C263: Lumberjackie Sherpa Vest | D263: Faded Amber | E263: XL | F263: 60 | G263: 119.95 | I263: =H263*F263 -> 0
A264: 7330057030310 | B264: A00236086-XXL | C264: Lumberjackie Sherpa Vest | D264: Faded Amber | E264: XXL | F264: 60 | G264: 119.95 | I264: =H264*F264 -> 0
A265: 7330057030327 | B265: A00236087-XXS | C265: Lumberjackie Sherpa Vest | D265: Faded Cloud | E265: XXS | F265: 60 | G265: 119.95 | I265: =H265*F265 -> 0
A266: 7330057026283 | B266: A00236087-XS | C266: Lumberjackie Sherpa Vest | D266: Faded Cloud | E266: XS | F266: 60 | G266: 119.95 | I266: =H266*F266 -> 0
A267: 7330057026290 | B267: A00236087-S | C267: Lumberjackie Sherpa Vest | D267: Faded Cloud | E267: S | F267: 60 | G267: 119.95 | I267: =H267*F267 -> 0
A268: 7330057026306 | B268: A00236087-M | C268: Lumberjackie Sherpa Vest | D268: Faded Cloud | E268: M | F268: 60 | G268: 119.95 | I268: =H268*F268 -> 0
A269: 7330057026313 | B269: A00236087-L | C269: Lumberjackie Sherpa Vest | D269: Faded Cloud | E269: L | F269: 60 | G269: 119.95 | I269: =H269*F269 -> 0
A270: 7330057026320 | B270: A00236087-XL | C270: Lumberjackie Sherpa Vest | D270: Faded Cloud | E270: XL | F270: 60 | G270: 119.95 | I270: =H270*F270 -> 0
A271: 7330057030389 | B271: A00236087-XXL | C271: Lumberjackie Sherpa Vest | D271: Faded Cloud | E271: XXL | F271: 60 | G271: 119.95 | I271: =H271*F271 -> 0
A272: 7330057030396 | B272: A00236088-XXS | C272: Lumberjackie Sherpa Vest | D272: Faded Oak | E272: XXS | F272: 60 | G272: 119.95 | I272: =H272*F272 -> 0
A273: 7330057026337 | B273: A00236088-XS | C273: Lumberjackie Sherpa Vest | D273: Faded Oak | E273: XS | F273: 60 | G273: 119.95 | I273: =H273*F273 -> 0
A274: 7330057026344 | B274: A00236088-S | C274: Lumberjackie Sherpa Vest | D274: Faded Oak | E274: S | F274: 60 | G274: 119.95 | I274: =H274*F274 -> 0
A275: 7330057026351 | B275: A00236088-M | C275: Lumberjackie Sherpa Vest | D275: Faded Oak | E275: M | F275: 60 | G275: 119.95 | I275: =H275*F275 -> 0
A276: 7330057026368 | B276: A00236088-L | C276: Lumberjackie Sherpa Vest | D276: Faded Oak | E276: L | F276: 60 | G276: 119.95 | I276: =H276*F276 -> 0
A277: 7330057026375 | B277: A00236088-XL | C277: Lumberjackie Sherpa Vest | D277: Faded Oak | E277: XL | F277: 60 | G277: 119.95 | I277: =H277*F277 -> 0
A278: 7330057030457 | B278: A00236088-XXL | C278: Lumberjackie Sherpa Vest | D278: Faded Oak | E278: XXL | F278: 60 | G278: 119.95 | I278: =H278*F278 -> 0
A279: 7330057030464 | B279: A00236089-XXS | C279: Lumberjackie Sherpa Vest | D279: Faded Woodrose | E279: XXS | F279: 60 | G279: 119.95 | I279: =H279*F279 -> 0
A280: 7330057026382 | B280: A00236089-XS | C280: Lumberjackie Sherpa Vest | D280: Faded Woodrose | E280: XS | F280: 60 | G280: 119.95 | I280: =H280*F280 -> 0
A281: 7330057026399 | B281: A00236089-S | C281: Lumberjackie Sherpa Vest | D281: Faded Woodrose | E281: S | F281: 60 | G281: 119.95 | I281: =H281*F281 -> 0
A282: 7330057026405 | B282: A00236089-M | C282: Lumberjackie Sherpa Vest | D282: Faded Woodrose | E282: M | F282: 60 | G282: 119.95 | I282: =H282*F282 -> 0
A283: 7330057026412 | B283: A00236089-L | C283: Lumberjackie Sherpa Vest | D283: Faded Woodrose | E283: L | F283: 60 | G283: 119.95 | I283: =H283*F283 -> 0
A284: 7330057026429 | B284: A00236089-XL | C284: Lumberjackie Sherpa Vest | D284: Faded Woodrose | E284: XL | F284: 60 | G284: 119.95 | I284: =H284*F284 -> 0
A285: 7330057030525 | B285: A00236089-XXL | C285: Lumberjackie Sherpa Vest | D285: Faded Woodrose | E285: XXL | F285: 60 | G285: 119.95 | I285: =H285*F285 -> 0
G286: Total: | H286: =SUM(H216:H285) -> 0 | I286: =SUM(I216:I285) -> 0
A288: ACCESSORIES
A289: 7330057026436 | B289: A00237086-ONESIZ | C289: Tubular Sherpa Neckwarmer | D289: Faded Amber | E289: OS | F289: 18 | G289: 35.95 | I289: =H289*F289 -> 0
A290: 7330057026443 | B290: A00237087-ONESIZ | C290: Tubular Sherpa Neckwarmer | D290: Faded Cloud | E290: OS | F290: 18 | G290: 35.95 | I290: =H290*F290 -> 0
...
