Workbook
Name JET: [1]LUGGAGE!#REF!
Name JET: #REF!

Sheet Summary
B2: 2022-2023 L1 PREMIUM GOODS USA BOOKING PROGRAM
B4: BILL TO: | E4: PO#
E6: TOTAL:
B9: SHIP TO: | F9: DEADLINE - January 21, 2022
B15: ORDER SUMMARY:
C16: THEOREM | E16: MENS FOUNDATION | G16: WOMEN'S FOUNDATION
C17: ='L1'!I214 -> 0 | E17: ='L1'!I572 -> 0 | F17: ='L1'!I865 -> 0
C19: APPAREL | E19: HANDWEAR | G19: HEADWEAR
C20: ='L1'!I1070 -> 0 | E20: ='L1'!I1153 -> 0 | G20: ='L1'!I1184 -> 0
B22: ORDER TOTAL: | C22: =C17+E17+F17+C20+E20+G20 -> 0
B25: Notes:
B36: Contact:
A37: Foundry Distribution - 3602 Via Terra Street, Salt Lake City, Utah 84115
A38: p. 801.994.6484 e. info@foundrydist.com

Sheet Policy
B2: L1 PREMIUM GOODS
B3: DISCOUNT STRUCTURE AND POLICY
B5: SOFTGOODS & ACCESSORIES | C5: ORDER TOTAL | D5: VOLUME DISCOUNT
B6: *To qualify for preseason softgoods booking terms a minimum order of $10, 000 must be made by order deadline. | C6: $ 10, 001 - $ 20, 000 | D6: 0.03
B7: *All orders are subject to availability. | C7: $ 20, 001 - $ 50, 000 | D7: 0.04
B8: *Orders received after booking deadline will not be eligible for discounts. | C8: $ 50, 001 - $ 80, 000 | D8: 0.05
C9: $ 80, 001 + | D9: 0.06
B11: BONUS DISCOUNTS | D11: DISCOUNT
B12: * Factory Deadline Discount: Orders Received by booking Dealine of January 21st, 2022. | D12: 0.02
B14: M.A.P POLICY
B15: March 1st, 2023 - MAP Down to 20% Off
B16: April 1, 2023 - MAP Down to 30% Off
B17: May 1, 2023 - MAP Down to 40% Off
B19: CREDIT TERMS & LIMITS
B20: * To receive discounts order MUST be submitted by order deadline. All product is Subject To Prior Sale
B21: * Booking terms are Net 30 from the date of delivery (On Approved Credit) If minimum booking volume is not met.
B22: * Booking terms are Net 90 Days If booking minimum booking volume is met.
B23: * After the expiration date all backorders will be shipped on regular terms.
B24: * To qualify for L1 Premium Goods Booking Terms, your account must be current in good standing.
B25: * Discounts may be given as a credit at time of on-time payment, for dealers with previous payment history concerns.
B26: * Pricing may be adjusted for currency decline and tarrif structure changes.
... B52: ALL SALES ARE SUBJECT TO TERMS AND CONDITIONS OF NITRO SNOWBOARDS AUTHORIZED DEALER APPLICATION

Sheet L1
A1: UPC | B1: SKU | C1: PRODUCT | D1: COLOUR | E1: SIZE | F1: WHSL | G1: RETAIL | H1: QUANTITY | I1: EXT
A3: THEORUM -MENS
A4: 7630221827877 | B4: N873850-001S | C4: 2023 ALPHA | D4: PHANTOM | E4: S | F4: 230 | G4: 459.95 | I4: =H4*F4 -> 0
A5: 7630221827884 | B5: N873850-001M | C5: 2023 ALPHA | D5: PHANTOM | E5: M | F5: 230 | G5: 459.95 | I5: =H5*F5 -> 0
A6: 7630221827891 | B6: N873850-001L | C6: 2023 ALPHA | D6: PHANTOM | E6: L | F6: 230 | G6: 459.95 | I6: =H6*F6 -> 0
A7: 7630221827907 | B7: N873850-001XL | C7: 2023 ALPHA | D7: PHANTOM | E7: XL | F7: 230 | G7: 459.95 | I7: =H7*F7 -> 0
A8: 7630221827914 | B8: N873850-001XXL | C8: 2023 ALPHA | D8: PHANTOM | E8: XXL | F8: 230 | G8: 459.95 | I8: =H8*F8 -> 0
A9: 7630221827921 | B9: N873850-002S | C9: 2023 ALPHA | D9: CHILI | E9: S | F9: 230 | G9: 459.95 | I9: =H9*F9 -> 0
A10: 7630221827938 | B10: N873850-002M | C10: 2023 ALPHA | D10: CHILI | E10: M | F10: 230 | G10: 459.95 | I10: =H10*F10 -> 0
A11: 7630221827945 | B11: N873850-002L | C11: 2023 ALPHA | D11: CHILI | E11: L | F11: 230 | G11: 459.95 | I11: =H11*F11 -> 0
A12: 7630221827952 | B12: N873850-002XL | C12: 2023 ALPHA | D12: CHILI | E12: XL | F12: 230 | G12: 459.95 | I12: =H12*F12 -> 0
A13: 7630221827969 | B13: N873850-002XXL | C13: 2023 ALPHA | D13: CHILI | E13: XXL | F13: 230 | G13: 459.95 | I13: =H13*F13 -> 0
A14: 7630221827976 | B14: N873850-003S | C14: 2023 ALPHA | D14: MOSS | E14: S | F14: 230 | G14: 459.95 | I14: =H14*F14 -> 0
A15: 7630221827983 | B15: N873850-003M | C15: 2023 ALPHA | D15: MOSS | E15: M | F15: 230 | G15: 459.95 | I15: =H15*F15 -> 0
... A93: 7630221830709 | B93: N873866-003XXL | C93: 2023 GEMINI | D93: MOSS | E93: XXL | F93: 175 | G93: 349.95 | I93: =H93*F93 -> 0
A94: THEORUM -UNISEX
A95: 7630221828171 | B95: N873852-001XS | C95: 2023 AXIAL JACKET | D95: PHANTOM | E95: XS | F95: 200 | G95: 399.95 | I95: =H95*F95 -> 0
A96: 7630221828188 | B96: N873852-001S | C96: 2023 AXIAL JACKET | D96: PHANTOM | E96: S | F96: 200 | G96: 399.95 | I96: =H96*F96 -> 0
A97: 7630221828195 | B97: N873852-001M | C97: 2023 AXIAL JACKET | D97: PHANTOM | E97: M | F97: 200 | G97: 399.95 | I97: =H97*F97 -> 0
A98: 7630221828201 | B98: N873852-001L | C98: 2023 AXIAL JACKET | D98: PHANTOM | E98: L | F98: 200 | G98: 399.95 | I98: =H98*F98 -> 0
A99: 7630221828218 | B99: N873852-001XL | C99: 2023 AXIAL JACKET | D99: PHANTOM | E99: XL | F99: 200 | G99: 399.95 | I99: =H99*F99 -> 0
A100: 7630221828225 | B100: N873852-001XXL | C100: 2023 AXIAL JACKET | D100: PHANTOM | E100: XXL | F100: 200 | G100: 399.95 | I100: =H100*F100 -> 0
A101: 7630221828232 | B101: N873852-002XS | C101: 2023 AXIAL JACKET | D101: SPRAY | E101: XS | F101: 200 | G101: 399.95 | I101: =H101*F101 -> 0
A102: 7630221828249 | B102: N873852002S | C102: 2023 AXIAL JACKET | D102: SPRAY | E102: S | F102: 200 | G102: 399.95 | I102: =H102*F102 -> 0
A103: 7630221828256 | B103: N873852002M | C103: 2023 AXIAL JACKET | D103: SPRAY | E103: M | F103: 200 | G103: 399.95 | I103: =H103*F103 -> 0
A104: 7630221828263 | B104: N873852002L | C104: 2023 AXIAL JACKET | D104: SPRAY | E104: L | F104: 200 | G104: 399.95 | I104: =H104*F104 -> 0
A105: 7630221828270 | B105: N873852002XL | C105: 2023 AXIAL JACKET | D105: SPRAY | E105: XL | F105: 200 | G105: 399.95 | I105: =H105*F105 -> 0
A106: 7630221828287 | B106: N873852002XXL | C106: 2023 AXIAL JACKET | D106: SPRAY | E106: XXL | F106: 200 | G106: 399.95 | I106: =H106*F106 -> 0
... A142: 7630221830945 | B142: N873867-004XXL | C142: 2023 AXIAL PANT | D142: ULTRAVIOLET | E142: XXL | F142: 175 | G142: 349.95 | I142: =H142*F142 -> 0
A143: THEORUM - WOMEN'S
A144: 7630221832802 | B144: N873878-001XS | C144: 2023 NIGHTWAVE | D144: MOSS | E144: XS | F144: 230 | G144: 459.95 | I144: =H144*F144 -> 0
A145: 7630221832819 | B145: N873878-001S | C145: 2023 NIGHTWAVE | D145: MOSS | E145: S | F145: 230 | G145: 459.95 | I145: =H145*F145 -> 0
A146: 7630221832826 | B146: N873878-001M | C146: 2023 NIGHTWAVE | D146: MOSS | E146: M | F146: 230 | G146: 459.95 | I146: =H146*F146 -> 0
A147: 7630221832833 | B147: N873878-001L | C147: 2023 NIGHTWAVE | D147: MOSS | E147: L | F147: 230 | G147: 459.95 | I147: =H147*F147 -> 0
A148: 7630221847790 | B148: N873878-001XL | C148: 2023 NIGHTWAVE | D148: MOSS | E148: XL | F148: 230 | G148: 459.95 | I148: =H148*F148 -> 0
A149: 7630221832840 | B149: N873878-002XS | C149: 2023 NIGHTWAVE | D149: ULTRAVIOLET | E149: XS | F149: 230 | G149: 459.95 | I149: =H149*F149 -> 0
A150: 7630221832857 | B150: N873878-002S | C150: 2023 NIGHTWAVE | D150: ULTRAVIOLET | E150: S | F150: 230 | G150: 459.95 | I150: =H150*F150 -> 0
A151: 7630221832864 | B151: N873878-002M | C151: 2023 NIGHTWAVE | D151: ULTRAVIOLET | E151: M | F151: 230 | G151: 459.95 | I151: =H151*F151 -> 0
A152: 7630221832871 | B152: N873878-002L | C152: 2023 NIGHTWAVE | D152: ULTRAVIOLET | E152: L | F152: 230 | G152: 459.95 | I152: =H152*F152 -> 0
A153: 7630221847806 | B153: N873878-002XL | C153: 2023 NIGHTWAVE | D153: ULTRAVIOLET | E153: XL | F153: 230 | G153: 459.95 | I153: =H153*F153 -> 0
A154: 7630221832888 | B154: N873878-003XS | C154: 2023 NIGHTWAVE | D154: PHANTOM | E154: XS | F154: 230 | G154: 459.95 | I154: =H154*F154 -> 0
A155: 7630221832895 | B155: N873878-003S | C155: 2023 NIGHTWAVE | D155: PHANTOM | E155: S | F155: 230 | G155: 459.95 | I155: =H155*F155 -> 0
... A213: 7630221848254 | B213: N873892-003XL | C213: 2023 COSMIC AGE | D213: SLATE | E213: XL | F213: 165 | G213: 329.95 | I213: =H213*F213 -> 0
G214: Total: | H214: =SUM(H4:H213) -> 0 | I214: =SUM(I4:I213) -> 0
A216: FOUNDATION -MENS
A217: 7630221828669 | B217: N873855-001S | C217: 2023 WILLIAMS | D217: PHANTOM - BLACK | E217: S | F217: 160 | G217: 319.95 | I217: =H217*F217 -> 0
A218: 7630221828676 | B218: N873855-001M | C218: 2023 WILLIAMS | D218: PHANTOM - BLACK | E218: M | F218: 160 | G218: 319.95 | I218: =H218*F218 -> 0
A219: 7630221828683 | B219: N873855-001L | C219: 2023 WILLIAMS | D219: PHANTOM - BLACK | E219: L | F219: 160 | G219: 319.95 | I219: =H219*F219 -> 0
A220: 7630221828690 | B220: N873855-001XL | C220: 2023 WILLIAMS | D220: PHANTOM - BLACK | E220: XL | F220: 160 | G220: 319.95 | I220: =H220*F220 -> 0
A221: 7630221828706 | B221: N873855-001XXL | C221: 2023 WILLIAMS | D221: PHANTOM - BLACK | E221: XXL | F221: 160 | G221: 319.95 | I221: =H221*F221 -> 0
A222: 7630221828713 | B222: N873855-002S | C222: 2023 WILLIAMS | D222: PLATOON | E222: S | F222: 160 | G222: 319.95 | I222: =H222*F222 -> 0
A223: 7630221828720 | B223: N873855-002M | C223: 2023 WILLIAMS | D223: PLATOON | E223: M | F223: 160 | G223: 319.95 | I223: =H223*F223 -> 0
A224: 7630221828737 | B224: N873855-002L | C224: 2023 WILLIAMS | D224: PLATOON | E224: L | F224: 160 | G224: 319.95 | I224: =H224*F224 -> 0
A225: 7630221828744 | B225: N873855-002XL | C225: 2023 WILLIAMS | D225: PLATOON | E225: XL | F225: 160 | G225: 319.95 | I225: =H225*F225 -> 0
A226: 7630221828751 | B226: N873855-002XXL | C226: 2023 WILLIAMS | D226: PLATOON | E226: XXL | F226: 160 | G226: 319.95 | I226: =H226*F226 -> 0
A227: 7630221828768 | B227: N873855-003S | C227: 2023 WILLIAMS | D227: AMBER - BLACK | E227: S | F227: 160 | G227: 319.95 | I227: =H227*F227 -> 0
A228: 7630221828775 | B228: N873855-003M | C228: 2023 WILLIAMS | D228: AMBER - BLACK | E228: M | F228: 160 | G228: 319.95 | I228: =H228*F228 -> 0
... A571: 7630221832598 | B571: N873876-002XXL | C571: 2023 ONYX FLEECE PANT | D571: SLATE - PHANTOM | E571: XXL | F571: 75 | G571: 149.95 | I571: =H571*F571 -> 0
G572: Total: | H572: =SUM(H217:H571) -> 0 | I572: =SUM(I217:I571) -> 0
A574: FOUNDATION - WOMEN'S
A575: 7630221833120 | B575: N873881-001XS | C575: 2023 FAIRBANKS | D575: PHANTOM | E575: XS | F575: 150 | G575: 299.95 | I575: =H575*F575 -> 0
A576: 7630221833137 | B576: N873881-001S | C576: 2023 FAIRBANKS | D576: PHANTOM | E576: S | F576: 150 | G576: 299.95 | I576: =H576*F576 -> 0
A577: 7630221833144 | B577: N873881-001M | C577: 2023 FAIRBANKS | D577: PHANTOM | E577: M | F577: 150 | G577: 299.95 | I577: =H577*F577 -> 0
A578: 7630221833151 | B578: N873881-001L | C578: 2023 FAIRBANKS | D578: PHANTOM | E578: L | F578: 150 | G578: 299.95 | I578: =H578*F578 -> 0
A579: 7630221847875 | B579: N873881-001XL | C579: 2023 FAIRBANKS | D579: PHANTOM | E579: XL | F579: 150 | G579: 299.95 | I579: =H579*F579 -> 0
A580: 7630221833168 | B580: N873881-002XS | C580: 2023 FAIRBANKS | D580: BURNT ROSE | E580: XS | F580: 150 | G580: 299.95 | I580: =H580*F580 -> 0
A581: 7630221833175 | B581: N873881-002S | C581: 2023 FAIRBANKS | D581: BURNT ROSE | E581: S | F581: 150 | G581: 299.95 | I581: =H581*F581 -> 0
A582: 7630221833182 | B582: N873881-002M | C582: 2023 FAIRBANKS | D582: BURNT ROSE | E582: M | F582: 150 | G582: 299.95 | I582: =H582*F582 -> 0
A583: 7630221833199 | B583: N873881-002L | C583: 2023 FAIRBANKS | D583: BURNT ROSE | E583: L | F583: 150 | G583: 299.95 | I583: =H583*F583 -> 0
A584: 7630221847882 | B584: N873881-002XL | C584: 2023 FAIRBANKS | D584: BURNT ROSE | E584: XL | F584: 150 | G584: 299.95 | I584: =H584*F584 -> 0
A585: 7630221833205 | B585: N873881-003XS | C585: 2023 FAIRBANKS | D585: GHOSTED PRINT | E585: XS | F585: 150 | G585: 299.95 | I585: =H585*F585 -> 0
A586: 7630221833212 | B586: N873881-003S | C586: 2023 FAIRBANKS | D586: GHOSTED PRINT | E586: S | F586: 150 | G586: 299.95 | I586: =H586*F586 -> 0
... A864: 7630221848506 | B864: N873898-004XL | C864: 2023 KYRA PANT | D864: STONE | E864: XL | F864: 95 | G864: 189.95 | I864: =H864*F864 -> 0
G865: Total: | H865: =SUM(H575:H864) -> 0 | I865: =SUM(I575:I864) -> 0
A867: APPAREL
A868: 7630221836473 | B868: N874152-001S | C868: 2023 L1 BLOCK ZIP HOODIE | D868: PHANTOM | E868: S | F868: 40 | G868: 79.95 | I868: =H868*F868 -> 0
A869: 7630221836480 | B869: N874152-001M | C869: 2023 L1 BLOCK ZIP HOODIE | D869: PHANTOM | E869: M | F869: 40 | G869: 79.95 | I869: =H869*F869 -> 0
A870: 7630221836497 | B870: N874152-001L | C870: 2023 L1 BLOCK ZIP HOODIE | D870: PHANTOM | E870: L | F870: 40 | G870: 79.95 | I870: =H870*F870 -> 0
A871: 7630221836503 | B871: N874152-001XL | C871: 2023 L1 BLOCK ZIP HOODIE | D871: PHANTOM | E871: XL | F871: 40 | G871: 79.95 | I871: =H871*F871 -> 0
A872: 7630221836510 | B872: N874152-001XXL | C872: 2023 L1 BLOCK ZIP HOODIE | D872: PHANTOM | E872: XXL | F872: 40 | G872: 79.95 | I872: =H872*F872 -> 0
A873: 7630221836527 | B873: N874152-002S | C873: 2023 L1 BLOCK ZIP HOODIE | D873: RUST | E873: S | F873: 40 | G873: 79.95 | I873: =H873*F873 -> 0
A874: 7630221836534 | B874: N874152-002M | C874: 2023 L1 BLOCK ZIP HOODIE | D874: RUST | E874: M | F874: 40 | G874: 79.95 | I874: =H874*F874 -> 0
A875: 7630221836541 | B875: N874152-002L | C875: 2023 L1 BLOCK ZIP HOODIE | D875: RUST | E875: L | F875: 40 | G875: 79.95 | I875: =H875*F875 -> 0
A876: 7630221836558 | B876: N874152-002XL | C876: 2023 L1 BLOCK ZIP HOODIE | D876: RUST | E876: XL | F876: 40 | G876: 79.95 | I876: =H876*F876 -> 0
A877: 7630221836565 | B877: N874152-002XXL | C877: 2023 L1 BLOCK ZIP HOODIE | D877: RUST | E877: XXL | F877: 40 | G877: 79.95 | I877: =H877*F877 -> 0
A878: 7630221836572 | B878: N874153-001S | C878: 2023 L1 OFF SIDE PO HOODIE | D878: STONE | E878: S | F878: 40 | G878: 79.95 | I878: =H878*F878 -> 0
A879: 7630221836589 | B879: N874153-001M | C879: 2023 L1 OFF SIDE PO HOODIE | D879: STONE | E879: M | F879: 40 | G879: 79.95 | I879: =H879*F879 -> 0
... A1069: 7630221838644 | B1069: N874175-002L | C1069: L1 MAE CROP TEE | D1069: PHANTOM | E1069: L | F1069: 14 | G1069: 27.95 | I1069: =H1069*F1069 -> 0
G1070: Total: | H1070: =SUM(H868:H1069) -> 0 | I1070: =SUM(I868:I1069) -> 0
A1072: HANDWEAR
A1073: 7630221826757 | B1073: N876025-001S | C1073: L1 SABBRA MEN Glove | D1073: BLACK | E1073: S | F1073: 35 | G1073: 69.95 | I1073: =H1073*F1073 -> 0
A1074: 7630221826764 | B1074: N876025-001M | C1074: L1 SABBRA MEN Glove | D1074: BLACK | E1074: M | F1074: 35 | G1074: 69.95 | I1074: =H1074*F1074 -> 0
A1075: 7630221826771 | B1075: N876025-001L | C1075: L1 SABBRA MEN Glove | D1075: BLACK | E1075: L | F1075: 35 | G1075: 69.95 | I1075: =H1075*F1075 -> 0
A1076: 7630221826788 | B1076: N876025-001XL | C1076: L1 SABBRA MEN Glove | D1076: BLACK | E1076: XL | F1076: 35 | G1076: 69.95 | I1076: =H1076*F1076 -> 0
A1077: 7630221826795 | B1077: N876025-002S | C1077: L1 SABBRA MEN Glove | D1077: AMBER | E1077: S | F1077: 35 | G1077: 69.95 | I1077: =H1077*F1077 -> 0
A1078: 7630221826801 | B1078: N876025-002M | C1078: L1 SABBRA MEN Glove | D1078: AMBER | E1078: M | F1078: 35 | G1078: 69.95 | I1078: =H1078*F1078 -> 0
A1079: 7630221826818 | B1079: N876025-002L | C1079: L1 SABBRA MEN Glove | D1079: AMBER | E1079: L | F1079: 35 | G1079: 69.95 | I1079: =H1079*F1079 -> 0
A1080: 7630221826825 | B1080: N876025-002XL | C1080: L1 SABBRA MEN Glove | D1080: AMBER | E1080: XL | F1080: 35 | G1080: 69.95 | I1080: =H1080*F1080 -> 0
A1081: 7630221826832 | B1081: N876025-003S | C1081: L1 SABBRA MEN Glove | D1081: SLATE | E1081: S | F1081: 35 | G1081: 69.95 | I1081: =H1081*F1081 -> 0
A1082: 7630221826849 | B1082: N876025-003M | C1082: L1 SABBRA MEN Glove | D1082: SLATE | E1082: M | F1082: 35 | G1082: 69.95 | I1082: =H1082*F1082 -> 0
...
