Workbook

Sheet Summary
B2: 2026-2027 NITRO SNOWBOARDS PACKAGES USA BOOKING PROGRAM
B4: BILL TO : | E4: P.O # :
F8: ORDER DEADLINES :
B9: SHIP TO : | F9: PACKAGES: JANUARY 23 2026
F11: Terms must be met to qualify for packages discounts
B14: ORDER SUMMARY :
C16: PRIME RAW | D16: PRIME CHROMA | E16: LECTRA ABSTRACT | F16: LECTRA LEAF | G16: RIPPER | H16: SPIRIT
C17: ='2026-2027 Nitro Packages'!O16 -> 0 | D17: ='2026-2027 Nitro Packages'!O26 -> 0 | E17: ='2026-2027 Nitro Packages'!O34 -> 0 | F17: ='2026-2027 Nitro Packages'!O42 -> 0 | G17: ='2026-2027 Nitro Packages'!O53 -> 0 | H17: ='2026-2027 Nitro Packages'!O64 -> 0
B18: 15% DISCOUNT EXT: | C18: =C17*0.85 -> 0 | D18: =D17*0.85 -> 0 | E18: =E17*0.85 -> 0 | F18: =F17*0.85 -> 0 | G18: =G17*0.85 -> 0 | H18: =H17*0.85 -> 0
B20: ORDER TOTAL : | C20: =C17+D17+E17+F17+G17+H17 -> 0 | D20: EXT : | E20: =C18+D18+E18+F18+G18+H18 -> 0
B22: NOTES :
B31: FOUNDRY DISTRIBUTION
B32: 3602 Via Terra Street, Salt Lake City, Utah 84115
B33: p. 801.994.6484 e. office@foundrydist.com

Sheet Terms
B2: NITRO SNOWBOARDS - Discount Structure and Policy
B4: ADULT PACKAGE
B5: Package must be advertised above Prime $499.95, $469.95 Lectra but can't be discounted and advertised seperately
B6: Package must be purchased 1:1:1 (board to binding to bag)
B7: Packages may be sold for 20% off at any time
B8: MAP Guidline to be followed if these items are sold seperately
B9: Existing shops must increase their order from last year by 5% or more to qualify for this program.
B10: Preseason discount does not apply to this package buy, or dealer level, or growth discount
B11: Deadline is January 23, 2026 for all orders to partake in this program - no package order will be accepted after this date
B13: KIDS PROGRAM
B14: Package must be advertised and sold for Normal Dealer Price
B15: Package must be purchased 1:1. Must submit $7,500 inline reg booking program to partake
... B62: *ALL SALES ARE SUBJECT TO TERMS AND CONDITIONS OF NITRO SNOWBOARDS AUTHORIZED DEALER APPLICATION

Sheet 2026-2027 Nitro Packages
A1: BRAND | B1: GENDER | C1: CATEGORY | D1: PACKAGE | E1: DISCOUNT | F1: UPC | G1: SKU | H1: DESCRIPTION | I1: COLOUR | J1: SIZE | K1: WHSL | L1: RETAIL | M1: QUANTITY | N1: EXT
B3: 2026-2027 NITRO US - PACKAGES
A5: ADULT PACKAGES MUST BE PURCHASED 1:1:1 (BOARD:BINDING:BAG) KIDS PACKAGES PACKAGES MUST BE PURCHASED 1:1 (BOARD:BINDING)
A7: Nitro | B7: Mens | C7: Snowboard | D7: PRIME RAW PACKAGE | E7: 0.1 | F7: 7630349321974 | G7: N833225-001149 | H7: 2027 PRIME RAW | I7: N/A - Carry Over | J7: 149 | K7: 228 | L7: 379.95 | N7: =M7*K7 -> 0
A8: Nitro | B8: Mens | C8: Snowboard | D8: PRIME RAW PACKAGE | E8: 0.1 | F8: 7630349321981 | G8: N833225-001152 | H8: 2027 PRIME RAW | I8: N/A - Carry Over | J8: 152 | K8: 228 | L8: 379.95 | N8: =M8*K8 -> 0
A9: Nitro | B9: Mens | C9: Snowboard | D9: PRIME RAW PACKAGE | E9: 0.1 | F9: 7630349321998 | G9: N833225-001155 | H9: 2027 PRIME RAW | I9: N/A - Carry Over | J9: 155 | K9: 228 | L9: 379.95 | N9: =M9*K9 -> 0
A10: Nitro | B10: Mens | C10: Snowboard | D10: PRIME RAW PACKAGE | E10: 0.1 | F10: 7630349322001 | G10: N833225-001158 | H10: 2027 PRIME RAW | I10: N/A - Carry Over | J10: 158 | K10: 228 | L10: 379.95 | N10: =M10*K10 -> 0
A11: Nitro | B11: Mens | C11: Snowboard | D11: PRIME RAW PACKAGE | E11: 0.1 | F11: 7630349322056 | G11: N833226-001156 | H11: 2027 PRIME RAW WIDE | I11: N/A - Carry Over | J11: 156 | K11: 228 | L11: 379.95 | N11: =M11*K11 -> 0
A12: Nitro | B12: Mens | C12: Snowboard | D12: PRIME RAW PACKAGE | E12: 0.1 | F12: 7630349322063 | G12: N833226-001160 | H12: 2027 PRIME RAW WIDE | I12: N/A - Carry Over | J12: 160 | K12: 228 | L12: 379.95 | N12: =M12*K12 -> 0
A13: Nitro | B13: Mens | C13: Snowboard | D13: PRIME RAW PACKAGE | E13: 0.1 | F13: 7630349322070 | G13: N833226-001164 | H13: 2027 PRIME RAW WIDE | I13: N/A - Carry Over | J13: 164 | K13: 228 | L13: 379.95 | N13: =M13*K13 -> 0
A14: Nitro | B14: Mens | C14: Bindings | D14: PRIME RAW PACKAGE | E14: 0.1 | F14: 7630349335056 | G14: N12BG11007-102M | H14: 2027 RAMBLER | I14: RAW | J14: M (7-10.5 MENS) | K14: 156 | L14: 259.95 | N14: =M14*K14 -> 0
A15: Nitro | B15: Mens | C15: Bindings | D15: PRIME RAW PACKAGE | E15: 0.1 | F15: 7630349335063 | G15: N12BG11007-102L | H15: 2027 RAMBLER | I15: RAW | J15: L (11-14 MENS) | K15: 156 | L15: 259.95 | N15: =M15*K15 -> 0
A16: Nitro | B16: Unisex | C16: Gear Bags | D16: PRIME RAW PACKAGE | E16: 0.1 | F16: 7630349335667 | G16: N878093-138OS | H16: 2027 LIGHT SACK 165 CM | I16: RAVEN | J16: 165 CM | K16: 27 | L16: 54.95 | N16: =M16*K16 -> 0 | O16: =SUM(N7:N16) -> 0
A17: Nitro | B17: Mens | C17: Snowboard | D17: PRIME CHROMA PACKAGE | E17: 0.1 | F17: 7630349352299 | G17: N11SB11020-101149 | H17: 2027 PRIME CHROMA | I17: N/A - Carry Forward | J17: 149 | K17: 228 | L17: 379.95 | N17: =M17*K17 -> 0
A18: Nitro | B18: Mens | C18: Snowboard | D18: PRIME CHROMA PACKAGE | E18: 0.1 | F18: 7630349352305 | G18: N11SB11020-101152 | H18: 2027 PRIME CHROMA | I18: N/A - Carry Forward | J18: 152 | K18: 228 | L18: 379.95 | N18: =M18*K18 -> 0
A19: Nitro | B19: Mens | C19: Snowboard | D19: PRIME CHROMA PACKAGE | E19: 0.1 | F19: 7630349352312 | G19: N11SB11020-101155 | H19: 2027 PRIME CHROMA | I19: N/A - Carry Forward | J19: 155 | K19: 228 | L19: 379.95 | N19: =M19*K19 -> 0
A20: Nitro | B20: Mens | C20: Snowboard | D20: PRIME CHROMA PACKAGE | E20: 0.1 | F20: 7630349352336 | G20: N11SB11020-101158 | H20: 2027 PRIME CHROMA | I20: N/A - Carry Forward | J20: 158 | K20: 228 | L20: 379.95 | N20: =M20*K20 -> 0
A21: Nitro | B21: Mens | C21: Snowboard | D21: PRIME CHROMA PACKAGE | E21: 0.1 | F21: 7630349352329 | G21: N11SB11020-101156W | H21: 2027 PRIME CHROMA | I21: N/A - Carry Forward | J21: 156W | K21: 228 | L21: 379.95 | N21: =M21*K21 -> 0
A22: Nitro | B22: Mens | C22: Snowboard | D22: PRIME CHROMA PACKAGE | E22: 0.1 | F22: 7630349352343 | G22: N11SB11020-101160W | H22: 2027 PRIME CHROMA | I22: N/A - Carry Forward | J22: 160W | K22: 228 | L22: 379.95 | N22: =M22*K22 -> 0
A23: Nitro | B23: Mens | C23: Snowboard | D23: PRIME CHROMA PACKAGE | E23: 0.1 | F23: 7630349352350 | G23: N11SB11020-101164W | H23: 2027 PRIME CHROMA | I23: N/A - Carry Forward | J23: 164W | K23: 228 | L23: 379.95 | N23: =M23*K23 -> 0
A24: Nitro | B24: Unisex | C24: Bindings | D24: PRIME CHROMA PACKAGE | E24: 0.1 | F24: 7630349335100 | G24: N12BG41008-101M | H24: 2027 TALENT | I24: ULTRA BLACK | J24: M (7-10.5 MENS) | K24: 120 | L24: 199.95 | N24: =M24*K24 -> 0
A25: Nitro | B25: Unisex | C25: Bindings | D25: PRIME CHROMA PACKAGE | E25: 0.1 | F25: 7630349335117 | G25: N12BG41008-101L | H25: 2027 TALENT | I25: ULTRA BLACK | J25: L (11-14 MENS) | K25: 120 | L25: 199.95 | N25: =M25*K25 -> 0
A26: Nitro | B26: Unisex | C26: Gear Bags | D26: PRIME CHROMA PACKAGE | E26: 0.1 | F26: 7630349335667 | G26: N878093-138OS | H26: 2027 LIGHT SACK 165 CM | I26: RAVEN | J26: 165 CM | K26: 27 | L26: 54.95 | N26: =M26*K26 -> 0 | O26: =SUM(N17:N26) -> 0
A27: Nitro | B27: Womens | C27: Snowboard | D27: LECTRA ABSTRACT PACKAGE | E27: 0.1 | F27: 7630349323039 | G27: N833241-001138 | H27: 2027 LECTRA ABSTRACT | I27: N/A - Carry Over | J27: 138 | K27: 228 | L27: 379.95 | N27: =M27*K27 -> 0
A28: Nitro | B28: Womens | C28: Snowboard | D28: LECTRA ABSTRACT PACKAGE | E28: 0.1 | F28: 7630349323046 | G28: N833241-001142 | H28: 2027 LECTRA ABSTRACT | I28: N/A - Carry Over | J28: 142 | K28: 228 | L28: 379.95 | N28: =M28*K28 -> 0
A29: Nitro | B29: Womens | C29: Snowboard | D29: LECTRA ABSTRACT PACKAGE | E29: 0.1 | F29: 7630349323053 | G29: N833241-001146 | H29: 2027 LECTRA ABSTRACT | I29: N/A - Carry Over | J29: 146 | K29: 228 | L29: 379.95 | N29: =M29*K29 -> 0
A30: Nitro | B30: Womens | C30: Snowboard | D30: LECTRA ABSTRACT PACKAGE | E30: 0.1 | F30: 7630349323060 | G30: N833241-001149 | H30: 2027 LECTRA ABSTRACT | I30: N/A - Carry Over | J30: 149 | K30: 228 | L30: 379.95 | N30: =M30*K30 -> 0
A31: Nitro | B31: Womens | C31: Snowboard | D31: LECTRA ABSTRACT PACKAGE | E31: 0.1 | F31: 7630349323077 | G31: N833241-001152 | H31: 2027 LECTRA ABSTRACT | I31: N/A - Carry Over | J31: 152 | K31: 228 | L31: 379.95 | N31: =M31*K31 -> 0
A32: Nitro | B32: Unisex | C32: Bindings | D32: LECTRA ABSTRACT PACKAGE | E32: 0.1 | F32: 7630349335124 | G32: N12BG41008-102S | H32: 2027 TALENT | I32: WHITE | J32: S (4-7.5 WMNS) | K32: 120 | L32: 199.95 | N32: =M32*K32 -> 0
A33: Nitro | B33: Unisex | C33: Bindings | D33: LECTRA ABSTRACT PACKAGE | E33: 0.1 | F33: 7630349335131 | G33: N12BG41008-102M | H33: 2027 TALENT | I33: WHITE | J33: M (8-11.5 WMNS) | K33: 120 | L33: 199.95 | N33: =M33*K33 -> 0
A34: Nitro | B34: Unisex | C34: Gear Bags | D34: LECTRA ABSTRACT PACKAGE | E34: 0.1 | F34: 7630349335667 | G34: N878093-138OS | H34: 2027 LIGHT SACK 165 CM | I34: RAVEN | J34: 165 CM | K34: 27 | L34: 54.95 | N34: =M34*K34 -> 0 | O34: =SUM(N27:N34) -> 0
A35: Nitro | B35: Womens | C35: Snowboard | D35: LECTRA LEAF PACKAGE | E35: 0.1 | F35: 7630349354095 | G35: N11SB21032-101138 | H35: 2027 LECTRA LEAF | I35: N/A - Carry Forward | J35: 138 | K35: 228 | L35: 379.95 | N35: =M35*K35 -> 0
A36: Nitro | B36: Womens | C36: Snowboard | D36: LECTRA LEAF PACKAGE | E36: 0.1 | F36: 7630349354101 | G36: N11SB21032-101142 | H36: 2027 LECTRA LEAF | I36: N/A - Carry Forward | J36: 142 | K36: 228 | L36: 379.95 | N36: =M36*K36 -> 0
A37: Nitro | B37: Womens | C37: Snowboard | D37: LECTRA LEAF PACKAGE | E37: 0.1 | F37: 7630349354118 | G37: N11SB21032-101146 | H37: 2027 LECTRA LEAF | I37: N/A - Carry Forward | J37: 146 | K37: 228 | L37: 379.95 | N37: =M37*K37 -> 0
A38: Nitro | B38: Womens | C38: Snowboard | D38: LECTRA LEAF PACKAGE | E38: 0.1 | F38: 7630349354125 | G38: N11SB21032-101149 | H38: 2027 LECTRA LEAF | I38: N/A - Carry Forward | J38: 149 | K38: 228 | L38: 379.95 | N38: =M38*K38 -> 0
A39: Nitro | B39: Womens | C39: Snowboard | D39: LECTRA LEAF PACKAGE | E39: 0.1 | F39: 7630349354132 | G39: N11SB21032-101152 | H39: 2027 LECTRA LEAF | I39: N/A - Carry Forward | J39: 152 | K39: 228 | L39: 379.95 | N39: =M39*K39 -> 0
A40: Nitro | B40: Unisex | C40: Bindings | D40: LECTRA LEAF PACKAGE | E40: 0.1 | F40: 7630349335124 | G40: N12BG41008-102S | H40: 2027 TALENT | I40: WHITE | J40: S (4-7.5 WMNS) | K40: 120 | L40: 199.95 | N40: =M40*K40 -> 0
A41: Nitro | B41: Unisex | C41: Bindings | D41: LECTRA LEAF PACKAGE | E41: 0.1 | F41: 7630349335131 | G41: N12BG41008-102M | H41: 2027 TALENT | I41: WHITE | J41: M (8-11.5 WMNS) | K41: 120 | L41: 199.95 | N41: =M41*K41 -> 0
A42: Nitro | B42: Unisex | C42: Gear Bags | D42: LECTRA LEAF PACKAGE | E42: 0.1 | F42: 7630349335667 | G42: N878093-138OS | H42: 2027 LIGHT SACK 165 CM | I42: RAVEN | J42: 165 CM | K42: 27 | L42: 54.95 | N42: =M42*K42 -> 0 | O42: =SUM(N35:N42) -> 0
A43: Nitro | B43: Youth | C43: Snowboard | D43: RIPPER PACKAGE | E43: 0.1 | F43: 7630349323770 | G43: N833252-001086 | H43: 2027 RIPPER KIDS | I43: N/A - Carry Over | J43: 086 | K43: 150 | L43: 249.95 | N43: =M43*K43 -> 0
A44: Nitro | B44: Youth | C44: Snowboard | D44: RIPPER PACKAGE | E44: 0.1 | F44: 7630349323787 | G44: N833252-001096 | H44: 2027 RIPPER KIDS | I44: N/A - Carry Over | J44: 096 | K44: 150 | L44: 249.95 | N44: =M44*K44 -> 0
A45: Nitro | B45: Youth | C45: Snowboard | D45: RIPPER PACKAGE | E45: 0.1 | F45: 7630349323794 | G45: N833252-001106 | H45: 2027 RIPPER KIDS | I45: N/A - Carry Over | J45: 106 | K45: 150 | L45: 249.95 | N45: =M45*K45 -> 0
A46: Nitro | B46: Youth | C46: Snowboard | D46: RIPPER PACKAGE | E46: 0.1 | F46: 7630349323800 | G46: N833252-001116 | H46: 2027 RIPPER KIDS | I46: N/A - Carry Over | J46: 116 | K46: 150 | L46: 249.95 | N46: =M46*K46 -> 0
A47: Nitro | B47: Youth | C47: Snowboard | D47: RIPPER PACKAGE | E47: 0.1 | F47: 7630349323817 | G47: N833252-001121 | H47: 2027 RIPPER KIDS | I47: N/A - Carry Over | J47: 121 | K47: 150 | L47: 249.95 | N47: =M47*K47 -> 0
A48: Nitro | B48: Youth | C48: Snowboard | D48: RIPPER PACKAGE | E48: 0.1 | F48: 7630349323824 | G48: N833252-001126 | H48: 2027 RIPPER KIDS | I48: N/A - Carry Over | J48: 126 | K48: 150 | L48: 249.95 | N48: =M48*K48 -> 0
A49: Nitro | B49: Youth | C49: Snowboard | D49: RIPPER PACKAGE | E49: 0.1 | F49: 7630349323893 | G49: N833253-001132 | H49: 2027 RIPPER YOUTH | I49: N/A - Carry Over | J49: 132 | K49: 162 | L49: 269.95 | N49: =M49*K49 -> 0
A50: Nitro | B50: Youth | C50: Snowboard | D50: RIPPER PACKAGE | E50: 0.1 | F50: 7630349323909 | G50: N833253-001137 | H50: 2027 RIPPER YOUTH | I50: N/A - Carry Over | J50: 137 | K50: 162 | L50: 269.95 | N50: =M50*K50 -> 0
A51: Nitro | B51: Youth | C51: Bindings | D51: RIPPER PACKAGE | E51: 0.1 | F51: 7630349335438 | G51: N12BG31014-101XS | H51: 2027 CHARGER MICRO | I51: ULTRA BLACK | J51: XS (12.0-2.5 KIDS) | K51: 78 | L51: 129.95 | N51: =M51*K51 -> 0
A52: Nitro | B52: Youth | C52: Bindings | D52: RIPPER PACKAGE | E52: 0.1 | F52: 7630349326146 | G52: N836532-001S | H52: 2027 CHARGER MINI | I52: ULTRA BLACK - Carry Over | J52: S (3.0-6.5 KIDS) | K52: 96 | L52: 159.95 | N52: =M52*K52 -> 0
A53: Nitro | B53: Unisex | C53: Bindings | D53: RIPPER PACKAGE | E53: 0.1 | F53: 7630349335094 | G53: N12BG41008-101S | H53: 2027 TALENT | I53: ULTRA BLACK | J53: S (3-6.5 MENS) | K53: 120 | L53: 199.95 | N53: =M53*K53 -> 0 | O53: =SUM(N43:N53) -> 0
A54: Nitro | B54: Youth | C54: Snowboard | D54: SPIRIT PACKAGE | E54: 0.1 | F54: 7630349355030 | G54: N11SB31042-101086 | H54: 2027 SPIRIT KIDS | I54: N/A - Carry Forward | J54: 086 | K54: 150 | L54: 249.95 | N54: =M54*K54 -> 0
A55: Nitro | B55: Youth | C55: Snowboard | D55: SPIRIT PACKAGE | E55: 0.1 | F55: 7630349355047 | G55: N11SB31042-101096 | H55: 2027 SPIRIT KIDS | I55: N/A - Carry Forward | J55: 096 | K55: 150 | L55: 249.95 | N55: =M55*K55 -> 0
A56: Nitro | B56: Youth | C56: Snowboard | D56: SPIRIT PACKAGE | E56: 0.1 | F56: 7630349355054 | G56: N11SB31042-101106 | H56: 2027 SPIRIT KIDS | I56: N/A - Carry Forward | J56: 106 | K56: 150 | L56: 249.95 | N56: =M56*K56 -> 0
A57: Nitro | B57: Youth | C57: Snowboard | D57: SPIRIT PACKAGE | E57: 0.1 | F57: 7630349355061 | G57: N11SB31042-101116 | H57: 2027 SPIRIT KIDS | I57: N/A - Carry Forward | J57: 116 | K57: 150 | L57: 249.95 | N57: =M57*K57 -> 0
A58: Nitro | B58: Youth | C58: Snowboard | D58: SPIRIT PACKAGE | E58: 0.1 | F58: 7630349355078 | G58: N11SB31042-101121 | H58: 2027 SPIRIT KIDS | I58: N/A - Carry Forward | J58: 121 | K58: 150 | L58: 249.95 | N58: =M58*K58 -> 0
A59: Nitro | B59: Youth | C59: Snowboard | D59: SPIRIT PACKAGE | E59: 0.1 | F59: 7630349355085 | G59: N11SB31042-101126 | H59: 2027 SPIRIT KIDS | I59: N/A - Carry Forward | J59: 126 | K59: 150 | L59: 249.95 | N59: =M59*K59 -> 0
A60: Nitro | B60: Youth | C60: Snowboard | D60: SPIRIT PACKAGE | E60: 0.1 | F60: 7630349354996 | G60: N11SB31041-101132 | H60: 2027 SPIRIT YOUTH | I60: N/A - Carry Forward | J60: 132 | K60: 162 | L60: 269.95 | N60: =M60*K60 -> 0
A61: Nitro | B61: Youth | C61: Snowboard | D61: SPIRIT PACKAGE | E61: 0.1 | F61: 7630349355009 | G61: N11SB31041-101137 | H61: 2027 SPIRIT YOUTH | I61: N/A - Carry Forward | J61: 137 | K61: 162 | L61: 269.95 | N61: =M61*K61 -> 0
A62: Nitro | B62: Youth | C62: Bindings | D62: SPIRIT PACKAGE | E62: 0.1 | F62: 7630349335445 | G62: N12BG31014-102XS | H62: 2027 CHARGER MICRO | I62: WHITE | J62: XS (12.0-2.5 KIDS) | K62: 78 | L62: 129.95 | N62: =M62*K62 -> 0
A63: Nitro | B63: Youth | C63: Bindings | D63: SPIRIT PACKAGE | E63: 0.1 | F63: 7630349326153 | G63: N836532-002S | H63: 2027 CHARGER MINI | I63: WHITE - Carry Over | J63: S (3.0-6.5 KIDS) | K63: 96 | L63: 159.95 | N63: =M63*K63 -> 0
A64: Nitro | B64: Unisex | C64: Bindings | D64: SPIRIT PACKAGE | E64: 0.1 | F64: 7630349335124 | G64: N12BG41008-102S | H64: 2027 TALENT | I64: WHITE | J64: S (3-6.5 MENS) | K64: 120 | L64: 199.95 | N64: =M64*K64 -> 0 | O64: =SUM(N54:N64) -> 0
